TestLib/__init__.py
TestLib/functions.py
RAtesting-0.0.1.dist-info/METADATA
RAtesting-0.0.1.dist-info/WHEEL
RAtesting-0.0.1.dist-info/top_level.txt
RAtesting-0.0.1.dist-info/RECORD
