Metadata-Version: 2.1
Name: RAtesting
Version: 0.0.1
Summary: Testing!
Home-page: UNKNOWN
Author: RA
License: UNKNOWN
Keywords: test
Platform: UNKNOWN
Classifier: Development Status :: 1 - Planning
Classifier: Intended Audience :: Developers
Classifier: Programming Language :: Python :: 3
Classifier: Operating System :: Microsoft :: Windows
Classifier: Operating System :: Unix
